nestedfacts.py
__init__.py
nestedfacts-1.0.1.dist-info/WHEEL
nestedfacts-1.0.1.dist-info/top_level.txt
nestedfacts-1.0.1.dist-info/zip-safe
nestedfacts-1.0.1.dist-info/metadata.json
nestedfacts-1.0.1.dist-info/METADATA
nestedfacts-1.0.1.dist-info/RECORD
nestedfacts-1.0.1.dist-info/DESCRIPTION.rst
