Metadata-Version: 2.0
Name: nestedfacts
Version: 1.0.1
Summary: This library enables users of Ansible to load nesteddirectories as local facts. Refer to the README formore details.
Home-page: https://github.com/uberspace/nestedfacts
Author: uberspace.de
Author-email: hallo@uberspace.de
License: MIT
Platform: UNKNOWN
Classifier: Development Status :: 4 - Beta
Classifier: Intended Audience :: Information Technology
Classifier: Intended Audience :: System Administrators
Classifier: Topic :: System :: Systems Administration
Classifier: Topic :: Utilities
Classifier: Natural Language :: English
Classifier: Operating System :: POSIX :: Linux
Classifier: License :: OSI Approved :: MIT License
Classifier: Programming Language :: Python :: Implementation :: CPython
Classifier: Programming Language :: Python :: 2.7
Classifier: Programming Language :: Python :: 3.5
Requires-Dist: pyyaml
